{
	"info": {
		"_postman_id": "009d8154-0c4c-451a-8708-799a36d3b47d",
		"name": "Prueba técnica",
		"schema": "https://schema.getpostman.com/json/collection/v2.1.0/collection.json",
		"_exporter_id": "40346764"
	},
	"item": [
		{
			"name": "GetClientWithLastOrderDateAndNextPredictedOrder",
			"request": {
				"auth": {
					"type": "noauth"
				},
				"method": "GET",
				"header": [],
				"url": {
					"raw": "http://localhost:5115/api/v1/customers/get-client-with-lastOrderDate-and-nextPredictedOrder",
					"protocol": "http",
					"host": [
						"localhost"
					],
					"port": "5115",
					"path": [
						"api",
						"v1",
						"customers",
						"get-client-with-lastOrderDate-and-nextPredictedOrder"
					]
				}
			},
			"response": []
		},
		{
			"name": "OrdersByCustomer",
			"request": {
				"method": "GET",
				"header": []
			},
			"response": []
		},
		{
			"name": "GetAllEmployees",
			"request": {
				"method": "GET",
				"header": []
			},
			"response": []
		},
		{
			"name": "GetAllShippers",
			"request": {
				"method": "GET",
				"header": []
			},
			"response": []
		},
		{
			"name": "GetAllProducts",
			"request": {
				"method": "GET",
				"header": [],
				"url": {
					"raw": "http://localhost:5115/api/v1/products/get-all",
					"protocol": "http",
					"host": [
						"localhost"
					],
					"port": "5115",
					"path": [
						"api",
						"v1",
						"products",
						"get-all"
					]
				}
			},
			"response": []
		},
		{
			"name": "CreateOrder",
			"request": {
				"method": "POST",
				"header": [],
				"body": {
					"mode": "raw",
					"raw": "{\r\n  \"EmpId\": 6,\r\n  \"CustId\": 71,\r\n  \"ShipperId\": 1,\r\n  \"ProductId\": 76,\r\n  \"ShipName\": \"John Doe\",\r\n  \"ShipAdress\": \"123 Main Street\",\r\n  \"ShipCity\": \"New York\",\r\n  \"OrderDate\": \"2024-02-28T14:30:00\",\r\n  \"RequiredDate\": \"2024-03-10T00:00:00\",\r\n  \"ShippedDate\": \"2024-03-05T16:00:00\",\r\n  \"Freight\": 15.75,\r\n  \"ShipCountry\": \"USA\",\r\n  \"UnitPrice\": 29.99,\r\n  \"Qty\": 3,\r\n  \"Discount\": 5.00\r\n}\r\n",
					"options": {
						"raw": {
							"language": "json"
						}
					}
				},
				"url": {
					"raw": "http://localhost:5115/api/v1/orders/create-order",
					"protocol": "http",
					"host": [
						"localhost"
					],
					"port": "5115",
					"path": [
						"api",
						"v1",
						"orders",
						"create-order"
					]
				}
			},
			"response": []
		}
	]
}